README.md
setup.py
omegaup_cli.egg-info/PKG-INFO
omegaup_cli.egg-info/SOURCES.txt
omegaup_cli.egg-info/dependency_links.txt
omegaup_cli.egg-info/entry_points.txt
omegaup_cli.egg-info/requires.txt
omegaup_cli.egg-info/top_level.txt
src/__init__.py
src/__main__.py
src/cli.py
src/utils.py