Metadata-Version: 2.1
Name: omegaup-cli
Version: 0.1.1a8
Summary: CLI for OmegaUp users.
Home-page: https://github.com/Apocryphon-X/omegaup-cli
Author: Dante Mendoza Leyva (Apocryphon-X)
Author-email: apocryphon.x.contact@gmail.com
License: MIT
Platform: UNKNOWN
Classifier: Development Status :: 3 - Alpha
Classifier: Environment :: Console
Classifier: Programming Language :: Python
Classifier: Programming Language :: Python :: 3
Classifier: Programming Language :: Python :: 3.8
Classifier: Programming Language :: Python :: 3.9
Requires-Python: >=3.8
